README
setup.py
gitomatic/__init__.py
gitomatic/auth.py
gitomatic/base.py
gitomatic/configuration.py
gitomatic/keys.py
gitomatic/main.py
gitomatic/perms.py
gitomatic/repo.py
gitomatic.egg-info/PKG-INFO
gitomatic.egg-info/SOURCES.txt
gitomatic.egg-info/dependency_links.txt
gitomatic.egg-info/entry_points.txt
gitomatic.egg-info/requires.txt
gitomatic.egg-info/top_level.txt
gitomatic/test/__init__.py
gitomatic/test/test.py