Metadata-Version: 1.0
Name: gitomatic
Version: 0.5.9
Summary: Git management tool
Home-page: http://pypi.python.org/pypi/gitomatic/
Author: Jorge Eduardo Cardona
Author-email: jorge.cardona@nuagehq.com
License: BSD
Keywords: git
Platform: UNKNOWN
Classifier: Development Status :: 3 - Alpha
Classifier: License :: OSI Approved :: BSD License
